vmapper/__init__.py
vmapper/color.py
vmapper/meta_func.py
vmapper/vmapper.py
vmapper-0.1.0.dev202308060456.dist-info/METADATA
vmapper-0.1.0.dev202308060456.dist-info/WHEEL
vmapper-0.1.0.dev202308060456.dist-info/RECORD
